wdmtoolbox/message.wdm
wdmtoolbox/wdmtoolbox.py
wdmtoolbox/wdmutil.py
wdmtoolbox/_wdm_lib.cp310-win_amd64.dll.a
wdmtoolbox/_wdm_lib.cp310-win_amd64.pyd
wdmtoolbox/__init__.py
wdmtoolbox/toolbox_utils/src/toolbox_utils/tsutils.py
wdmtoolbox/toolbox_utils/src/toolbox_utils/__init__.py
wdmtoolbox/toolbox_utils/src/toolbox_utils/readers/hbn.py
wdmtoolbox/toolbox_utils/src/toolbox_utils/readers/plotgen.py
wdmtoolbox/toolbox_utils/src/toolbox_utils/readers/wdm.py
wdmtoolbox/toolbox_utils/src/toolbox_utils/readers/__init__.py
wdmtoolbox-16.0.12.dist-info/DELVEWHEEL
wdmtoolbox-16.0.12.dist-info/entry_points.txt
wdmtoolbox-16.0.12.dist-info/METADATA
wdmtoolbox-16.0.12.dist-info/RECORD
wdmtoolbox-16.0.12.dist-info/WHEEL
wdmtoolbox.libs/libgcc_s_seh-1-ff2c3d263053474784b94c5b4ae1830b.dll
wdmtoolbox.libs/libgfortran-5-9dd6c53a21ec07be02c2ddf74e1744e3.dll
wdmtoolbox.libs/libquadmath-0-277b68c87a650d1a2a73c6f4959d7d7e.dll
wdmtoolbox.libs/libwinpthread-1-10eb8498f1fe8f4674cffc211dc6c741.dll
