Metadata-Version: 2.1
Name: wdmtoolbox
Version: 16.0.12
Summary: Read and write Watershed Data Management (WDM) files
Keywords: HSPF,WDM,data,data_management,fortran,hydrological,hydrology,simulation,watershed
Author-Email: Tim Cera <tim@cerazone.net>
License: BSD-3-Clause
Classifier: Development Status :: 5 - Production/Stable
Classifier: Environment :: Console
Classifier: Intended Audience :: Developers
Classifier: Intended Audience :: End Users/Desktop
Classifier: Intended Audience :: Science/Research
Classifier: License :: OSI Approved :: BSD License
Classifier: Natural Language :: English
Classifier: Operating System :: OS Independent
Classifier: Programming Language :: Python :: 3 :: Only
Classifier: Programming Language :: Python :: 3.10
Classifier: Programming Language :: Python :: 3.11
Classifier: Programming Language :: Python :: 3.12
Classifier: Programming Language :: Python :: 3.13
Classifier: Programming Language :: Python :: 3.14
Classifier: Topic :: Scientific/Engineering :: Information Analysis
Classifier: Topic :: Scientific/Engineering
Classifier: Topic :: Software Development :: Libraries :: Python Modules
Project-URL: bitbucket, https://bitbucket.org/timcera/wdmtoolbox/src/main/
Project-URL: documentation, https://timcera.bitbucket.io/wdmtoolbox/docs/index.html
Project-URL: github, https://github.com/timcera/wdmtoolbox
Requires-Python: >=3.10
Requires-Dist: cltoolbox>=2.0.0
Requires-Dist: dateparser
Requires-Dist: filelock
Requires-Dist: numpy
Requires-Dist: packaging
Requires-Dist: pandas[excel]
Requires-Dist: pint!=0.21.*
Requires-Dist: pint-pandas
Requires-Dist: pydantic
Requires-Dist: python-dateutil
Requires-Dist: scipy
Requires-Dist: tabulate
